{
  "$schema": "https://json-schema.org/draft/2020-12/schema",
  "$id": "https://schemas.redevplugin.dev/plugin/error-codes-v1.schema.json",
  "title": "ReDevPlugin stable error codes v1",
  "type": "object",
  "additionalProperties": false,
  "$defs": {
    "platform_error_code": {
      "type": "string",
      "enum": [
        "PLUGIN_INVALID_REQUEST",
        "PLUGIN_MANIFEST_INVALID",
        "PLUGIN_PACKAGE_INVALID",
        "PLUGIN_PACKAGE_TOO_LARGE",
        "PLUGIN_PACKAGE_PATH_FORBIDDEN",
        "PLUGIN_SIGNATURE_INVALID",
        "PLUGIN_TRUST_STATE_DENIED",
        "PLUGIN_TRUST_VERIFICATION_REQUIRED",
        "PLUGIN_TRUST_VERIFICATION_INVALID",
        "PLUGIN_DISABLED",
        "PLUGIN_DISABLED_BY_POLICY",
        "PLUGIN_PERMISSION_DENIED",
        "PLUGIN_CONFIRMATION_REQUIRED",
        "PLUGIN_CONFIRMATION_INVALID",
        "PLUGIN_TOKEN_EXPIRED",
        "PLUGIN_TOKEN_REPLAY",
        "PLUGIN_GATEWAY_TOKEN_INVALID",
        "PLUGIN_GATEWAY_TOKEN_REPLAYED",
        "PLUGIN_GATEWAY_TOKEN_CHANNEL_MISMATCH",
        "PLUGIN_ASSET_TICKET_INVALID",
        "PLUGIN_ASSET_SESSION_INVALID",
        "PLUGIN_STREAM_TICKET_INVALID",
        "PLUGIN_STREAM_CANCELLED",
        "PLUGIN_LEASE_INVALID",
        "PLUGIN_LEASE_REPLAYED",
        "PLUGIN_GRANT_INVALID",
        "PLUGIN_STORAGE_QUOTA_EXCEEDED",
        "PLUGIN_OPERATION_BLOCKED",
        "PLUGIN_OPERATION_NOT_FOUND",
        "PLUGIN_OPERATION_NOT_CANCELABLE",
        "PLUGIN_NETWORK_TARGET_DENIED",
        "PLUGIN_NETWORK_RATE_LIMITED",
        "PLUGIN_RUNTIME_UNAVAILABLE",
        "PLUGIN_RUNTIME_VERSION_MISMATCH",
        "PLUGIN_JSON_LIMIT_EXCEEDED",
        "PLUGIN_CONTRACT_MISMATCH",
        "PLUGIN_CSRF_REQUIRED",
        "PLUGIN_RETAINED_DATA_CLEANUP_FAILED",
        "PLUGIN_RETAINED_DATA_BIND_FAILED"
      ]
    },
    "bridge_error_code": {
      "type": "string",
      "enum": [
        "PLUGIN_INVALID_REQUEST",
        "PLUGIN_MANIFEST_INVALID",
        "PLUGIN_PACKAGE_INVALID",
        "PLUGIN_PACKAGE_TOO_LARGE",
        "PLUGIN_PACKAGE_PATH_FORBIDDEN",
        "PLUGIN_SIGNATURE_INVALID",
        "PLUGIN_TRUST_STATE_DENIED",
        "PLUGIN_TRUST_VERIFICATION_REQUIRED",
        "PLUGIN_TRUST_VERIFICATION_INVALID",
        "PLUGIN_DISABLED",
        "PLUGIN_DISABLED_BY_POLICY",
        "PLUGIN_PERMISSION_DENIED",
        "PLUGIN_CONFIRMATION_REQUIRED",
        "PLUGIN_CONFIRMATION_INVALID",
        "PLUGIN_TOKEN_EXPIRED",
        "PLUGIN_TOKEN_REPLAY",
        "PLUGIN_GATEWAY_TOKEN_INVALID",
        "PLUGIN_GATEWAY_TOKEN_REPLAYED",
        "PLUGIN_GATEWAY_TOKEN_CHANNEL_MISMATCH",
        "PLUGIN_ASSET_TICKET_INVALID",
        "PLUGIN_ASSET_SESSION_INVALID",
        "PLUGIN_STREAM_TICKET_INVALID",
        "PLUGIN_STREAM_CANCELLED",
        "PLUGIN_LEASE_INVALID",
        "PLUGIN_LEASE_REPLAYED",
        "PLUGIN_GRANT_INVALID",
        "PLUGIN_STORAGE_QUOTA_EXCEEDED",
        "PLUGIN_OPERATION_BLOCKED",
        "PLUGIN_OPERATION_NOT_FOUND",
        "PLUGIN_OPERATION_NOT_CANCELABLE",
        "PLUGIN_NETWORK_TARGET_DENIED",
        "PLUGIN_NETWORK_RATE_LIMITED",
        "PLUGIN_RUNTIME_UNAVAILABLE",
        "PLUGIN_RUNTIME_VERSION_MISMATCH",
        "PLUGIN_JSON_LIMIT_EXCEEDED",
        "PLUGIN_CONTRACT_MISMATCH",
        "PLUGIN_CSRF_REQUIRED",
        "PLUGIN_RETAINED_DATA_CLEANUP_FAILED",
        "PLUGIN_RETAINED_DATA_BIND_FAILED",
        "PLUGIN_CONFIRMATION_REJECTED",
        "PLUGIN_BRIDGE_TIMEOUT",
        "PLUGIN_BRIDGE_DISPOSED",
        "PLUGIN_BRIDGE_HANDSHAKE_FAILED",
        "PLUGIN_BRIDGE_HANDSHAKE_REQUIRED"
      ]
    },
    "typescript_client_error_code": {
      "type": "string",
      "enum": [
        "PLUGIN_INVALID_REQUEST",
        "PLUGIN_MANIFEST_INVALID",
        "PLUGIN_PACKAGE_INVALID",
        "PLUGIN_PACKAGE_TOO_LARGE",
        "PLUGIN_PACKAGE_PATH_FORBIDDEN",
        "PLUGIN_SIGNATURE_INVALID",
        "PLUGIN_TRUST_STATE_DENIED",
        "PLUGIN_TRUST_VERIFICATION_REQUIRED",
        "PLUGIN_TRUST_VERIFICATION_INVALID",
        "PLUGIN_DISABLED",
        "PLUGIN_DISABLED_BY_POLICY",
        "PLUGIN_PERMISSION_DENIED",
        "PLUGIN_CONFIRMATION_REQUIRED",
        "PLUGIN_CONFIRMATION_INVALID",
        "PLUGIN_TOKEN_EXPIRED",
        "PLUGIN_TOKEN_REPLAY",
        "PLUGIN_GATEWAY_TOKEN_INVALID",
        "PLUGIN_GATEWAY_TOKEN_REPLAYED",
        "PLUGIN_GATEWAY_TOKEN_CHANNEL_MISMATCH",
        "PLUGIN_ASSET_TICKET_INVALID",
        "PLUGIN_ASSET_SESSION_INVALID",
        "PLUGIN_STREAM_TICKET_INVALID",
        "PLUGIN_STREAM_CANCELLED",
        "PLUGIN_LEASE_INVALID",
        "PLUGIN_LEASE_REPLAYED",
        "PLUGIN_GRANT_INVALID",
        "PLUGIN_STORAGE_QUOTA_EXCEEDED",
        "PLUGIN_OPERATION_BLOCKED",
        "PLUGIN_OPERATION_NOT_FOUND",
        "PLUGIN_OPERATION_NOT_CANCELABLE",
        "PLUGIN_NETWORK_TARGET_DENIED",
        "PLUGIN_NETWORK_RATE_LIMITED",
        "PLUGIN_RUNTIME_UNAVAILABLE",
        "PLUGIN_RUNTIME_VERSION_MISMATCH",
        "PLUGIN_JSON_LIMIT_EXCEEDED",
        "PLUGIN_CONTRACT_MISMATCH",
        "PLUGIN_CSRF_REQUIRED",
        "PLUGIN_RETAINED_DATA_CLEANUP_FAILED",
        "PLUGIN_RETAINED_DATA_BIND_FAILED",
        "PLUGIN_CONFIRMATION_REJECTED",
        "PLUGIN_BRIDGE_TIMEOUT",
        "PLUGIN_BRIDGE_DISPOSED",
        "PLUGIN_BRIDGE_HANDSHAKE_FAILED",
        "PLUGIN_BRIDGE_HANDSHAKE_REQUIRED",
        "PLUGIN_PLATFORM_REQUEST_FAILED",
        "PLUGIN_STREAM_FAILED"
      ]
    },
    "rust_ipc_error_code": {
      "type": "string",
      "enum": [
        "ARTIFACT_HANDLE_FAILED",
        "HANDLE_GRANT_VALIDATION_FAILED",
        "STORAGE_FILE_FAILED",
        "STORAGE_KV_FAILED",
        "STORAGE_SQLITE_FAILED",
        "NETWORK_GRANT_FAILED",
        "NETWORK_EXECUTE_FAILED",
        "NETWORK_STREAM_STORE_UNAVAILABLE",
        "NETWORK_STREAM_FAILED",
        "NETWORK_STREAM_BACKPRESSURE",
        "NETWORK_STREAM_INVALID",
        "NETWORK_STREAM_NOT_FOUND",
        "NETWORK_STREAM_CLOSED",
        "WORKER_INVOCATION_INVALID",
        "RUNTIME_CAPABILITY_REVOKED",
        "RUNTIME_CONTROL_CHANNEL_STALE",
        "RUNTIME_LEASE_SIGNATURE_INVALID",
        "PLUGIN_LEASE_REPLAYED",
        "WASM_NOT_IMPLEMENTED",
        "WASM_WORKER_INVALID",
        "WASM_HOSTCALL_FAILED",
        "UNSUPPORTED_FRAME"
      ]
    }
  }
}
